easy_jupyter_editor_mcp/__init__.py
easy_jupyter_editor_mcp-0.1.0.dist-info/METADATA
easy_jupyter_editor_mcp-0.1.0.dist-info/WHEEL
easy_jupyter_editor_mcp-0.1.0.dist-info/entry_points.txt
easy_jupyter_editor_mcp-0.1.0.dist-info/RECORD
