Metadata-Version: 2.4
Name: easy-jupyter-editor-mcp
Version: 0.1.0
Summary: A structural Jupyter Notebook Editor MCP server
Requires-Python: >=3.10
Requires-Dist: mcp[cli]
Requires-Dist: nbformat
